CHANGES.txt
CONTRIBUTORS.txt
MANIFEST.in
README.rst
bootstrap-buildout.py
bootstrap.py
buildout.cfg
setup.py
docs/LICENSE.GPL
docs/LICENSE.txt
src/aws/__init__.py
src/aws.authrss.egg-info/PKG-INFO
src/aws.authrss.egg-info/SOURCES.txt
src/aws.authrss.egg-info/dependency_links.txt
src/aws.authrss.egg-info/entry_points.txt
src/aws.authrss.egg-info/namespace_packages.txt
src/aws.authrss.egg-info/not-zip-safe
src/aws.authrss.egg-info/requires.txt
src/aws.authrss.egg-info/top_level.txt
src/aws/authrss/__init__.py
src/aws/authrss/config.py
src/aws/authrss/configure.zcml
src/aws/authrss/interfaces.py
src/aws/authrss/tokenmanager.py
src/aws/authrss/utils.py
src/aws/authrss/browser/__init__.py
src/aws/authrss/browser/configure.zcml
src/aws/authrss/browser/viewlets.py
src/aws/authrss/browser/views.py
src/aws/authrss/browser/templates/controlpanel.pt
src/aws/authrss/browser/templates/personal_token.pt
src/aws/authrss/browser/templates/rsslink.pt
src/aws/authrss/locales/README.txt
src/aws/authrss/locales/aws.authrss.pot
src/aws/authrss/locales/updatelocales.py
src/aws/authrss/locales/fr/LC_MESSAGES/aws.authrss.mo
src/aws/authrss/locales/fr/LC_MESSAGES/aws.authrss.po
src/aws/authrss/profiles/default/actions.xml
src/aws/authrss/profiles/default/browserlayer.xml
src/aws/authrss/profiles/default/componentregistry.xml
src/aws/authrss/profiles/default/controlpanel.xml
src/aws/authrss/profiles/default/metadata.xml
src/aws/authrss/profiles/default/rolemap.xml
src/aws/authrss/tests/__init__.py
src/aws/authrss/tests/resources.py
src/aws/authrss/tests/test_doctests.py
src/aws/authrss/tests/test_installation.py
src/aws/authrss/tests/test_tokenmanager.py
src/aws/authrss/tests/test_utils.py
src/aws/authrss/tests/test_views.py
src/aws/authrss/tests/use_cases.txt