Metadata-Version: 1.1
Name: aws.authrss
Version: 2.0.1
Summary: Private Plone RSS feeds through a user private token
Home-page: http://pypi.python.org/pypi/aws.authrss
Author: Gilles Lenfant
Author-email: gilles.lenfant@alterway.fr
License: GPL
Keywords: plone rss
Platform: UNKNOWN
Classifier: License :: OSI Approved :: GNU General Public License (GPL)
Classifier: Programming Language :: Python :: 2.7
Classifier: Framework :: Plone
Classifier: Framework :: Plone :: 4.3
Classifier: Framework :: Plone :: 5.0
Classifier: Natural Language :: English
Classifier: Natural Language :: French
